[
    {
        "bank": "Actors FCU",
        "_7DayAverage": "5.000",
        "_14DayAverage": "5.000",
        "_30DayAverage": "5.000",
        "_60DayAverage": "4.825",
        "_365DayAverage": "3.254"
    },
    {
        "bank": "Associated Bank",
        "_7DayAverage": "5.911",
        "_14DayAverage": "6.009",
        "_30DayAverage": "6.300",
        "_60DayAverage": "6.446",
        "_365DayAverage": "4.666"
    },
    {
        "bank": "Bank5",
        "_7DayAverage": "6.000",
        "_14DayAverage": "6.089",
        "_30DayAverage": "6.375",
        "_60DayAverage": "6.412",
        "_365DayAverage": "213.821"
    },
    {
        "bank": "Bethpage FCU",
        "_7DayAverage": "4.893",
        "_14DayAverage": "4.964",
        "_30DayAverage": "5.046",
        "_60DayAverage": "5.242",
        "_365DayAverage": "3.840"
    },
    {
        "bank": "CFCU",
        "_7DayAverage": "4.125",
        "_14DayAverage": "4.170",
        "_30DayAverage": "4.200",
        "_60DayAverage": "4.033",
        "_365DayAverage": "2.844"
    },
    {
        "bank": "Ent CU",
        "_7DayAverage": "5.607",
        "_14DayAverage": "5.661",
        "_30DayAverage": "5.732",
        "_60DayAverage": "6.059",
        "_365DayAverage": "4.437"
    },
    {
        "bank": "First Tech Federal",
        "_7DayAverage": "6.304",
        "_14DayAverage": "6.393",
        "_30DayAverage": "6.617",
        "_60DayAverage": "6.825",
        "_365DayAverage": "4.917"
    },
    {
        "bank": "Ozark Bank",
        "_7DayAverage": "5.804",
        "_14DayAverage": "5.875",
        "_30DayAverage": "6.025",
        "_60DayAverage": "6.088",
        "_365DayAverage": "4.814*"
    },
    {
        "bank": "US Bank",
        "_7DayAverage": "5.500",
        "_14DayAverage": "5.616",
        "_30DayAverage": "5.778",
        "_60DayAverage": "5.889",
        "_365DayAverage": "4.467"
    }
]